{ "main" : "objdump_modules/objdump.o.bc"
  , "binary"  : "objdump_slashed"
  , "modules"    : [
	  "objdump_modules/dwarf.o.bc",
	  "objdump_modules/prdbg.o.bc",
	  "objdump_modules/rddbg.o.bc",
	  "objdump_modules/debug.o.bc",
	  "objdump_modules/binutils_stabs.o.bc",
	  "objdump_modules/rdcoff.o.bc",
	  "objdump_modules/bucomm.o.bc",
	  "objdump_modules/version.o.bc",
	  "objdump_modules/filemode.o.bc",
	  "objdump_modules/elfcomm.o.bc",
	  "objdump_modules/disassemble.o.bc",
	  "objdump_modules/dis-init.o.bc",
	  "objdump_modules/i386-dis.o.bc",
	  "objdump_modules/dis-buf.o.bc",
	  "objdump_modules/archive.o.bc",
	  "objdump_modules/archures.o.bc",
	  "objdump_modules/bfd.o.bc",
	  "objdump_modules/bfdio.o.bc",
	  "objdump_modules/coff-bfd.o.bc",
	  "objdump_modules/compress.o.bc",
	  "objdump_modules/elf-properties.o.bc",
	  "objdump_modules/format.o.bc",
	  "objdump_modules/hash.o.bc",
	  "objdump_modules/init.o.bc",
	  "objdump_modules/libbfd.o.bc",
	  "objdump_modules/opncls.o.bc",
	  "objdump_modules/section.o.bc",
	  "objdump_modules/simple.o.bc",
	  "objdump_modules/stab-syms.o.bc",
	  "objdump_modules/syms.o.bc",
	  "objdump_modules/targets.o.bc",
	  "objdump_modules/binary.o.bc",
	  "objdump_modules/ihex.o.bc",
	  "objdump_modules/srec.o.bc",
	  "objdump_modules/tekhex.o.bc",
	  "objdump_modules/verilog.o.bc",
	  "objdump_modules/elf64-x86-64.o.bc",
	  "objdump_modules/elfxx-x86.o.bc",
	  "objdump_modules/elf-ifunc.o.bc",
	  "objdump_modules/elf-nacl.o.bc",
	  "objdump_modules/elf64.o.bc",
	  "objdump_modules/elf.o.bc",
	  "objdump_modules/elflink.o.bc",
	  "objdump_modules/elf-attrs.o.bc",
	  "objdump_modules/elf-strtab.o.bc",
	  "objdump_modules/elf-eh-frame.o.bc",
	  "objdump_modules/dwarf1.o.bc",
	  "objdump_modules/dwarf2.o.bc",
	  "objdump_modules/elf32-i386.o.bc",
	  "objdump_modules/elf-vxworks.o.bc",
	  "objdump_modules/elf32.o.bc",
	  "objdump_modules/pei-i386.o.bc",
	  "objdump_modules/peigen.o.bc",
	  "objdump_modules/cofflink.o.bc",
	  "objdump_modules/coffgen.o.bc",
	  "objdump_modules/pei-x86_64.o.bc",
	  "objdump_modules/pex64igen.o.bc",
	  "objdump_modules/elf64-gen.o.bc",
	  "objdump_modules/elf32-gen.o.bc",
	  "objdump_modules/plugin.o.bc",
	  "objdump_modules/cpu-i386.o.bc",
	  "objdump_modules/cpu-iamcu.o.bc",
	  "objdump_modules/cpu-l1om.o.bc",
	  "objdump_modules/cpu-k1om.o.bc",
	  "objdump_modules/cpu-plugin.o.bc",
	  "objdump_modules/archive64.o.bc",
	  "objdump_modules/cache.o.bc",
	  "objdump_modules/corefile.o.bc",
	  "objdump_modules/linker.o.bc",
	  "objdump_modules/merge.o.bc",
	  "objdump_modules/reloc.o.bc",
	  "objdump_modules/bfd_stabs.o.bc",
	  "objdump_modules/libz_a-compress.o.bc",
	  "objdump_modules/libz_a-deflate.o.bc",
	  "objdump_modules/libz_a-inflate.o.bc",
	  "objdump_modules/libz_a-inftrees.o.bc",
	  "objdump_modules/libz_a-trees.o.bc",
	  "objdump_modules/libz_a-zutil.o.bc",
	  "objdump_modules/libz_a-adler32.o.bc",
	  "objdump_modules/libz_a-crc32.o.bc",
	  "objdump_modules/libz_a-inffast.o.bc",
	  "objdump_modules/cplus-dem.o.bc",
	  "objdump_modules/cp-demangle.o.bc",
	  "objdump_modules/argv.o.bc",
	  "objdump_modules/concat.o.bc",
	  "objdump_modules/cp-demint.o.bc",
	  "objdump_modules/d-demangle.o.bc",
	  "objdump_modules/dwarfnames.o.bc",
	  "objdump_modules/filename_cmp.o.bc",
	  "objdump_modules/getpwd.o.bc",
	  "objdump_modules/hashtab.o.bc",
	  "objdump_modules/hex.o.bc",
	  "objdump_modules/lbasename.o.bc",
	  "objdump_modules/lrealpath.o.bc",
	  "objdump_modules/make-relative-prefix.o.bc",
	  "objdump_modules/make-temp-file.o.bc",
	  "objdump_modules/objalloc.o.bc",
	  "objdump_modules/rust-demangle.o.bc",
	  "objdump_modules/safe-ctype.o.bc",
      "objdump_modules/unlink-if-ordinary.o.bc",
	  "objdump_modules/xexit.o.bc",
	  "objdump_modules/xmalloc.o.bc",
	  "objdump_modules/xstrdup.o.bc",
	  "objdump_modules/xstrerror.o.bc"
  ]
  , "native_libs" : []
  , "static_args"    : ["-D", "-t", "-s", "-w"]
  , "dynamic_args"    : "1"
  , "name"    : "objdump"
}
